{
  "parent": "minecraft:recipes/root",
  "criteria": {
    "has_the_recipe": {
      "conditions": {
        "recipe": "storm:weathered_spruce_slab"
      },
      "trigger": "minecraft:recipe_unlocked"
    },
    "has_weathered_spruce_planks": {
      "conditions": {
        "items": [
          {
            "items": [
              "storm:weathered_spruce_planks"
            ]
          }
        ]
      },
      "trigger": "minecraft:inventory_changed"
    }
  },
  "requirements": [
    [
      "has_weathered_spruce_planks",
      "has_the_recipe"
    ]
  ],
  "rewards": {
    "recipes": [
      "storm:weathered_spruce_slab"
    ]
  },
  "sends_telemetry_event": false
}